---
layout: post
title: "[Java] Primitive Type ë°ì´í„°ê°€ ì €ì¥ë˜ëŠ” ê³µê°„ì€ ì–´ë”œê¹Œ?"
subtitle: "javapë¡œ ë””ì–´ì…ˆë¸”í•˜ì—¬ Primitive type ë°ì´í„°ë¥¼ í™•ì¸í•´ë³´ì."
categories: devlog
tags: java primitive-type
---

> javap CMDë¥¼ ì‚¬ìš©í•˜ì—¬ ì–´ë–»ê²Œ ë™ì‘í•˜ëŠ”ì§€ ë¹„êµí•©ë‹ˆë‹¤.

<!--more-->

## ğŸŒ± Primitive Type ë°ì´í„°ë€?

Javaì—ì„œ Primitive Type ë°ì´í„°ëŠ” ì•„ì£¼ ê¸°ë³¸ì ì¸ íƒ€ì…, ë”ì´ìƒ ë‚˜ëˆŒ ìˆ˜ ì—†ëŠ” ë‹¨ìœ„ì˜ ë°ì´í„°ë¥¼ ì˜ë¯¸í•˜ë©° 8ê°€ì§€ì˜ ê¸°ë³¸ íƒ€ì… ë°ì´í„°ê°€ ì¡´ì¬í•©ë‹ˆë‹¤.

Primitive type ë°ì´í„°ì— ëŒ€í•œ ìì„¸í•œ ì •ë³´ëŠ” Javaì…ë¬¸ì„œì™€ ë¸”ë¡œê·¸ì—ì„œ í™•ì¸í•  ìˆ˜ ìˆì—ˆìœ¼ë‚˜, ì–´ë””ì— ì €ì¥ë˜ëŠ”ì§€ëŠ” ëª…í™•í•˜ê²Œ íŒŒì•…í•  ë°©ë²•ì´ ì—†ì—ˆìŠµë‹ˆë‹¤. ì´ì— 
ì´ë¥¼ ì•Œì•„ë³´ê³ ì í•©ë‹ˆë‹¤.

---

## ğŸŒ± ë¸”ë¡œê¹…ì˜ ë°œë‹¨

ì°¸ì¡°í˜• ë°ì´í„°ëŠ” ëŒ€ê°œ Heap ì˜ì—­ì— ì €ì¥ëœë‹¤ê³  ì•Œë ¤ì ¸ ìˆìŠµë‹ˆë‹¤. ê·¸ë¦¬ê³  Primitive type ë°ì´í„°ëŠ” JVM Stackì— ì €ì¥ëœë‹¤ê³  ì•Œë ¤ì ¸ ìˆìŠµë‹ˆë‹¤. í•˜ì§€ë§Œ ì‚¬ì‹¤ Primitive Type ë°ì´í„°ì—ëŠ” 
ë§ì€ ì´ì•¼ê¸°ë“¤ì´ ëŒê³  ìˆìŠµë‹ˆë‹¤.

- ì›ì‹œ íƒ€ì… ë°ì´í„° ë˜í•œ ì°¸ì¡°í˜• ë°ì´í„°ì²˜ëŸ¼ ì›ì‹œ íƒ€ì… ë°ì´í„°ê°€ ì €ì¥ëœ ë©”ëª¨ë¦¬ì˜ ì£¼ì†Œë¥¼ ë¹„êµí•œë‹¤.
- ì›ì‹œ íƒ€ì… ë°ì´í„°ëŠ” ì»´íŒŒì¼ ì‹œì ì— Constant Poolì— ì €ì¥ë˜ê³  ëŸ°íƒ€ì„ ì‹œì ì— Constant Poolì—ì„œ ì €ì¥ëœ ë°ì´í„°ì˜ ì£¼ì†Œë¥¼ JVM Stackì— ì €ì¥í•œë‹¤.
- ì›ì‹œ íƒ€ì… ë°ì´í„°ë¥¼ == ì—°ì‚°ìë¡œ ë¹„êµí•  ë•ŒëŠ” `ê°’`ì„ ë¹„êµí•˜ê³ , ì°¸ì¡°í˜• ë°ì´í„°ë¥¼ == ì—°ì‚°ìë¡œ ë¹„êµí•  ë•ŒëŠ” `ë°ì´í„° ì£¼ì†Œ`ë¥¼ ë¹„êµí•œë‹¤. (ê·¸ë˜ì„œ ì°¸ì¡°í˜• ë°ì´í„°ëŠ” equalsë¥¼ ì‚¬ìš©í•œë‹¤.)
- ë°˜ëŒ€ë¡œ ì›ì‹œ íƒ€ì… ë°ì´í„° ë˜í•œ == ì—°ì‚°ìë¡œ ë¹„êµí•  ë•Œ ë°ì´í„° ì£¼ì†Œë¥¼ ë¹„êµí•œë‹¤.
- í´ë˜ìŠ¤ ì•ˆì˜ ë§´ë²„ ë³€ìˆ˜ë¡œ ì„ ì–¸ëœ ì›ì‹œ íƒ€ì… ë°ì´í„°ëŠ” ê·¸ëŒ€ë¡œ Heapì— ì €ì¥ëœë‹¤.

ë“±ë“± ìˆ˜ë§ì€ ì •ë³´ë“¤ì„ ì ‘í•  ìˆ˜ ìˆëŠ”ë°.. ì–´ë–¤ ì •ë³´ëŠ” ë‹¤ë¥¸ ì •ë³´ì™€ ì •ë°˜ëŒ€ë˜ëŠ” ì˜ë¯¸ë¥¼ ê°€ì§€ê³  ìˆë‹¤ëŠ” ê²ƒì„ í™•ì¸í–ˆìŠµë‹ˆë‹¤. ê·¸ë˜ì„œ ì´ ë¶€ë¶„ì„ ëª…í™•í•˜ê²Œ ì •ë¦¬í•˜ê³  ì‹¶ì€ ìƒê°ì´ ë¸”ë¡œê¹…ì˜ ë°œë‹¨ì´ ë˜ì—ˆìŠµë‹ˆë‹¤.

----

## ğŸŒ± ì–´ë–»ê²Œ í™•ì¸í•  ìˆ˜ ìˆì„ê¹Œ?

> Java JDK 17ì„ ì‚¬ìš©í•˜ê³  ìˆìŠµë‹ˆë‹¤.

ê°’ì´ Constant Poolì— ì €ì¥ë˜ëŠ”ì§€ ê·¸ì € Stackì— ì €ì¥ë˜ëŠ”ì§€ ì‚¬ì‹¤ ê³µì‹ ë¬¸ì„œë¥¼ ì œì™¸í•˜ê³ ëŠ” ëª…í™•í•˜ê²Œ í™•ì¸í•  ë°©ë²•ì´ ì—†ì§€ ì•Šë‚˜ ìƒê°í–ˆìŠµë‹ˆë‹¤. í•˜ì§€ë§Œ javapë¡œ ë””ì–´ìƒ˜ë¸”ë§í•˜ì—¬ ì‹¤í–‰ë˜ëŠ” í´ë˜ìŠ¤ê°€ constant poolì— ì–´ë–¤ ê°’ì„ 
ì°¸ì¡°í•˜ê³  ìˆëŠ”ì§€ëŠ” íŒŒì•…í•  ìˆ˜ ìˆì§€ ì•Šì„ê¹Œ ìƒê°í•˜ì—¬ javapë¥¼ ì‚¬ìš©í•´ë³´ê¸°ë¡œ í–ˆìŠµë‹ˆë‹¤.

```java
public class Parent {

	static int b = 14;

	public static void main(String[] args) {
		int a = 11;

		int c = a + b;
	}
}
```

ì´ ì½”ë“œë¥¼ í†µí•´ ì—¬ëŸ¬ê°€ì§€ ê°€ì„¤ì„ ì„¸ì›Œë³´ì•˜ìŠµë‹ˆë‹¤.

- bì— í• ë‹¹ëœ 14ëŠ” Parentê°€ ë¡œë“œë  ë•Œ ì´ˆê¸°í™”ë˜ëŠ” static ë³€ìˆ˜ì´ë‹¤. static ë°ì´í„°ê°€ Heapì— ì €ì¥ë˜ëŠ”ì§€, Metaspaceì— ì €ì¥ë˜ëŠ”ì§€ (Java8 ì´í›„)ëŠ” [ë…¼ë€ì´ ë§ì€ ì£¼ì œë¼ê³  ìƒê°ë˜ì§€ë§Œ](https://stackoverflow.com/questions/8387989/where-are-static-methods-and-static-variables-stored-in-java),
ê²°êµ­ bëŠ” Parent ê°ì²´ì— í• ë‹¹ëœ ê°’ì´ê¸° ë•Œë¬¸ì— Constant Poolì´ ì•„ë‹Œ Parentë¡œë¶€í„° ì°¸ì¡°ë  ê²ƒì´ë‹¤.
- ë¡œì»¬ ë³€ìˆ˜ aì— í• ë‹¹ëœ 11ì€ Constant Poolì— ì €ì¥ë˜ì–´ ì°¸ì¡°ë˜ëŠ” ê²ƒì´ ì•„ë‹ˆë¼, Parentì˜ main ë©”ì†Œë“œê°€ ì»´íŒŒì¼ ë˜ì–´ ë°”ì´íŠ¸ì½”ë“œë¡œ ë³€í™˜ë  ë•Œ ìˆ˜ì§‘ëœ ì •ë³´ë¡œì¨, ë°”ì´íŠ¸ì½”ë“œê°€ ì‹¤í–‰ë  ë•Œ JVM stackì— ê° ë°ì´í„°ê°€ ì €ì¥ëœë‹¤.
- bì— í• ë‹¹ëœ ë°ì´í„°ëŠ” ì°¸ì¡°ë¥¼ í†µí•´, aì— í• ë‹¹ëœ ë°ì´í„°ëŠ” ë°”ì´íŠ¸ì½”ë“œë¥¼ í†µí•´ ì•Œ ìˆ˜ ìˆìœ¼ë©°, a + bì˜ ê²°ê³¼ì¸ cëŠ” JVM ìŠ¤íƒì—ì„œ ì—°ì‚°ëœ ê°’ì´ë¯€ë¡œ Constant Poolì— ì €ì¥ë  í•„ìš”ì—†ì´ JVM Stackì—ì„œ ì—°ì‚°ë˜ì–´ ì†Œëª¨ëœë‹¤. 

í•´ë‹¹ ê°€ì„¤ê³¼ í•¨ê»˜ ìœ„ì˜ ì½”ë“œë¥¼ javapë¡œ ë””ì–´ìƒ˜ë¸” í•´ë³´ì•˜ìŠµë‹ˆë‹¤.

```
Classfile ***
  Compiled from "Parent.java"
public class Parent
  minor version: 0
  major version: 61
  flags: (0x0021) ACC_PUBLIC, ACC_SUPER
  this_class: #8                          // Parent
  super_class: #2                         // java/lang/Object
  interfaces: 0, fields: 1, methods: 3, attributes: 1
Constant pool:
   #1 = Methodref          #2.#3          // java/lang/Object."<init>":()V
   #2 = Class              #4             // java/lang/Object
   #3 = NameAndType        #5:#6          // "<init>":()V
   #4 = Utf8               java/lang/Object
   #5 = Utf8               <init>
   #6 = Utf8               ()V
   #7 = Fieldref           #8.#9          // Parent.b:I
   #8 = Class              #10            // Parent
   #9 = NameAndType        #11:#12        // b:I
  #10 = Utf8               Parent
  #11 = Utf8               b
  #12 = Utf8               I
  #13 = Utf8               Code
  #14 = Utf8               LineNumberTable
  #15 = Utf8               main
  #16 = Utf8               ([Ljava/lang/String;)V
  #17 = Utf8               <clinit>
  #18 = Utf8               SourceFile
  #19 = Utf8               Parent.java
{
  static int b;
    descriptor: I
    flags: (0x0008) ACC_STATIC

  public Parent();
    descriptor: ()V
    flags: (0x0001) ACC_PUBLIC
    Code:
      stack=1, locals=1, args_size=1
         0: aload_0
         1: invokespecial #1                  // Method java/lang/Object."<init>":()V
         4: return
      LineNumberTable:
        line 1: 0

  public static void main(java.lang.String[]);
    descriptor: ([Ljava/lang/String;)V
    flags: (0x0009) ACC_PUBLIC, ACC_STATIC
    Code:
      stack=2, locals=3, args_size=1
         0: bipush        11
         2: istore_1
         3: iload_1
         4: getstatic     #7                  // Field b:I
         7: iadd
         8: istore_2
         9: return
      LineNumberTable:
        line 6: 0
        line 8: 3
        line 9: 9

  static {};
    descriptor: ()V
    flags: (0x0008) ACC_STATIC
    Code:
      stack=1, locals=0, args_size=0
         0: bipush        14
         2: putstatic     #7                  // Field b:I
         5: return
      LineNumberTable:
        line 3: 0
}
SourceFile: "Parent.java"
```

...

ë¨¼ì €, Constant Pool ì…ë‹ˆë‹¤.

```
Constant pool:
   #1 = Methodref          #2.#3          // java/lang/Object."<init>":()V
   #2 = Class              #4             // java/lang/Object
   #3 = NameAndType        #5:#6          // "<init>":()V
   #4 = Utf8               java/lang/Object
   #5 = Utf8               <init>
   #6 = Utf8               ()V
   #7 = Fieldref           #8.#9          // Parent.b:I
   #8 = Class              #10            // Parent
   #9 = NameAndType        #11:#12        // b:I
  #10 = Utf8               Parent
  #11 = Utf8               b
  #12 = Utf8               I
  #13 = Utf8               Code
  #14 = Utf8               LineNumberTable
  #15 = Utf8               main
  #16 = Utf8               ([Ljava/lang/String;)V
  #17 = Utf8               <clinit>
  #18 = Utf8               SourceFile
  #19 = Utf8               Parent.java
```

ì´ ë°”ì´íŠ¸ì½”ë“œë¥¼ ë³´ë©´ Constant Poolì— ì •ìˆ˜í˜• ë°ì´í„°ê°€ ì €ì¥ë˜ì–´ ìˆëŠ” ê²ƒì„ í™•ì¸í•  ìˆ˜ ì—†ìŠµë‹ˆë‹¤. Constant Poolì€ ëŒ€ê°œ íƒ€ì…, ì´ë¦„, ìƒìˆ˜ ë“±ì˜ ì •ë³´ë“¤ì„ ì €ì¥í•´ë†“ëŠ” ê³µê°„ì´ì§€ë§Œ, 
ìˆ«ìí˜• ë°ì´í„°ë¼ê³ í•´ì„œ ëª¨ë“  ë°ì´í„°ê°€ ìƒìˆ˜ê°€ ë˜ëŠ” ê²ƒì€ ì•„ë‹ˆë¼ëŠ” ê²ƒì„ í™•ì¸í•  ìˆ˜ ìˆì—ˆìŠµë‹ˆë‹¤.

"ê·¸ëƒ¥ ìƒìˆ˜í˜• ë°ì´í„°ëŠ” ì•ˆë‚˜ì˜¨ê±°ì¼ ìˆ˜ë„ ìˆì–ì•„ìš”!" ë¼ê³  í•  ìˆ˜ ìˆì„ ê²ƒ ê°™ì•„ main ë©”ì†Œë“œì— `String d = "hello"`ë¥¼ ì„ ì–¸í•´ë³´ì•˜ìŠµë‹ˆë‹¤.

```
#10 = Utf8               Parent
#13 = String             #14            // hello
#14 = Utf8               hello
#15 = Utf8               Code
```

ì‹ ê¸°í•˜ê²Œë„ helloë¼ëŠ” ë°ì´í„°ê°€ Constant Poolì— ì €ì¥ë˜ì–´ ìˆëŠ” ê²ƒì„ í™•ì¸í•  ìˆ˜ ìˆì—ˆìŠµë‹ˆë‹¤. Stringì„ ë¬¸ì ë¦¬í„°ëŸ´ ë°©ì‹ìœ¼ë¡œ ì„ ì–¸í•˜ë©´ Constant Poolì— ì €ì¥ë˜ëŠ” íŠ¹ì§•ì„ ê°€ì§€ê³  ìˆìŠµë‹ˆë‹¤. ì´ë¥¼ í†µí•´ 
ìˆ«ìí˜• ë°ì´í„°ê°€ Constant Poolì— ì €ì¥ë˜ì§€ ì•ŠëŠ”ë‹¤ëŠ” ê²ƒì„ ë°˜ì¦í•  ìˆ˜ ìˆìŠµë‹ˆë‹¤.

...

ê·¸ëŸ¼ 14, 11 ë“±ì˜ ë°ì´í„°ëŠ” ì–´ë””ì— ìˆì„ê¹Œìš”? 

```
public static void main(java.lang.String[]);
    descriptor: ([Ljava/lang/String;)V
    flags: (0x0009) ACC_PUBLIC, ACC_STATIC
    Code:
      stack=2, locals=4, args_size=1
         0: bipush        11
         2: istore_1
         3: iload_1
         4: getstatic     #7                  // Field b:I
         7: iadd
         8: istore_2
         9: ldc           #13                 // String hello
        11: astore_3
        12: return
      LineNumberTable:
        line 6: 0
        line 8: 3
        line 10: 9
        line 11: 12

  static {};
    descriptor: ()V
    flags: (0x0008) ACC_STATIC
    Code:
      stack=1, locals=0, args_size=0
         0: bipush        14
         2: putstatic     #7                  // Field b:I
         5: return
      LineNumberTable:
        line 3: 0
```

javapë¡œ ë³¼ ìˆ˜ ìˆëŠ” Constant Poolì´ì™¸ì— 2ê°€ì§€ ë°ì´í„°ëŠ” main ë©”ì†Œë“œê°€ ì‹¤í–‰ë  ë•Œ, static ë³€ìˆ˜ì— ê°’ì´ ì´ˆê¸°í™”ë  ë•Œ ì…ë‹ˆë‹¤. í•´ë‹¹ ë°”ì´íŠ¸ì½”ë“œë¥¼ ë³´ë©´, ì–´ë””ì—ì„œ ê°€ì ¸ì˜¨ì§€ë„ ëª¨ë¥¸ì²´ 
bipushë¡œ 11ê³¼ 14ë¥¼ ê°ê° JVM Stackì— ì €ì¥í•˜ëŠ” ê²ƒì„ ë³¼ ìˆ˜ ìˆìŠµë‹ˆë‹¤.

11ê³¼ 14 ë°ì´í„°ëŠ” Constant Poolì—ì„œ ì°¸ì¡°í•˜ì§€ ì•Šê³ , ë©”ì†Œë“œ ë‚´ì—ì„œ ì§ì ‘ ì²˜ë¦¬ë˜ëŠ” ê²ƒì„ í™•ì¸í•  ìˆ˜ ìˆìŠµë‹ˆë‹¤. ì¦‰, ë©”ì†Œë“œ ì •ë³´ë¡œ ê°’ì„ ê°€ì§€ê³  ìˆë‹¤ê°€ ëŸ°íƒ€ì„ ì‹œ ë°”ì´íŠ¸ì½”ë“œê°€ ì¸í„°í”„ë¦¬í„° ë“±ìœ¼ë¡œ í•´ì„ë  ë•Œ 
JVM Stackì— ì €ì¥ë˜ëŠ” ê²ƒì…ë‹ˆë‹¤.

---

## ğŸŒ± ìœ„ì˜ ë¶„ì„ì„ í†µí•´ ì–´ë–¤ ê²ƒì„ ì•Œê²Œ ë˜ì—ˆë‚˜ìš”?

ì›ì‹œ íƒ€ì… ë°ì´í„°ë¼ê³  í•´ì„œ ëª¨ë‘ Constant Poolì— ì €ì¥ë˜ëŠ” ê²ƒì€ ì•„ë‹™ë‹ˆë‹¤. ë˜í•œ, ëˆ„êµ°ê°€ ì‘ì„±í–ˆë˜ Constant Poolì— ì €ì¥ëœ ì›ì‹œ íƒ€ì… ë°ì´í„°ì˜ ì£¼ì†Œë¥¼ ë¹„êµí•˜ì—¬ ë™ì¼ì„±ì„ íŒë‹¨í•œë‹¤ëŠ” ê²ƒë„ ì‚¬ì‹¤ì´ ì•„ë‹˜ì„ ë³¼ ìˆ˜ ìˆì—ˆìŠµë‹ˆë‹¤.

ê²°ë¡ ìœ¼ë¡œ ì •ë¦¬í•  ìˆ˜ ìˆëŠ” ê²ƒë“¤ì€ ë‹¤ìŒê³¼ ê°™ìŠµë‹ˆë‹¤.

### ğŸŸ¤ ì§ì ‘ì ìœ¼ë¡œ ì•Œ ìˆ˜ ìˆì—ˆë˜ ê²ƒë“¤
- Primitive Type ë°ì´í„°ì˜ ë™ì¼ì„±ì„ ë¹„êµí•  ë•ŒëŠ” ì£¼ì†Œê°€ ì•„ë‹Œ `ê°’`ì„ ë¹„êµí•œë‹¤. (ì°¸ì¡°í˜• ë°ì´í„°ëŠ” ì£¼ì†Œê°’ì„ ë¹„êµí•˜ëŠ”ê²Œ ë§ë‹¤.)
- ë©”ì†Œë“œì—ì„œ ì—°ì‚°ë˜ì–´ ìƒˆë¡­ê²Œ ìƒì„±ë˜ëŠ” ë°ì´í„° (ex. int i = a + b)ëŠ” Constant Poolê°™ì€ ë³„ë„ì˜ ê³µê°„ì— í• ë‹¹ë˜ëŠ” ê²ƒì´ ì•„ë‹ˆë¼ JVM Stackì—ì„œ ì—°ì‚°ë˜ì–´ ë°”ë¡œ ì†Œëª¨ëœë‹¤.


### ğŸŸ¤ ê°„ì ‘ì ìœ¼ë¡œ ì•Œ ìˆ˜ ìˆì—ˆë˜ ê²ƒë“¤
- static ìœ¼ë¡œ ì„ ì–¸ëœ ë°ì´í„°ëŠ” Method Areaì˜ static ì˜ì—­ì— ì €ì¥ë˜ê³ , í´ë˜ìŠ¤ì˜ ë§´ë²„ ë³€ìˆ˜ë¡œ ì„ ì–¸ëœ ì›ì‹œ íƒ€ì… ë°ì´í„°ëŠ” ê°ì²´ ì¸ìŠ¤í„´ìŠ¤ì™€ í•¨ê»˜ Heap ì˜ì—­ì— ì €ì¥ëœë‹¤.
- Stringì€ Constant Poolì— ì„ ì–¸ëœ ë¬¸ìì—´ ê·¸ëŒ€ë¡œ ì €ì¥ë˜ê¸° ë•Œë¬¸ì— Stringê°’ì„ ë¬´ì°¨ë³„ì ìœ¼ë¡œ + ì—°ì‚°í•˜ë©´ Constant Poolì˜ ë©”ëª¨ë¦¬ ê³µê°„ì„ ë‚­ë¹„í•  ìˆ˜ ìˆë‹¤. (StringBuilder, StringBuffer ì‚¬ìš© ê¶Œì¥)

----

## ğŸŒ± ê²°ë¡ 

ì‚¬ì‹¤ ì´ë ‡ê²Œ ë¸”ë¡œê·¸ë¥¼ ì‘ì„±í–ˆì§€ë§Œ ìœ„ì˜ ê²°ê³¼ê°€ í‹€ë¦´ ìˆ˜ë„ ìˆìŠµë‹ˆë‹¤. ì§€ê¸ˆì€ oracleì—ì„œ ë§Œë“  Java 17ë²„ì „ì„ ì‚¬ìš©í•œ ê²°ê³¼ì´ì§€ë§Œ, Javaì˜ ì¢…ë¥˜ì™€ ì œê³µí•˜ëŠ” íšŒì‚¬ëŠ” ì—¬ëŸ¬ê°œ ì¡´ì¬í•œë‹¤. ìë°”ë¼ëŠ” í° ì¸í„°í˜ì´ìŠ¤ì—ì„œ ëª…ì„¸í•˜ëŠ” 
ê¸°ëŠ¥ì„ ì–´ë–¤ ë°©ì‹ìœ¼ë¡œ êµ¬í˜„í•œë‹¤ë©´ ê·¸ê²ƒì€ Javaì´ê¸° ë•Œë¬¸ì— ì„¸ë¶€ì ìœ¼ë¡œ ë™ì‘í•˜ëŠ” ì›ë¦¬ëŠ” ê° Java ì¢…ë¥˜ë§ˆë‹¤ ë‹¤ë¥¼ ìˆ˜ ìˆìŠµë‹ˆë‹¤.

> ë”°ë¼ì„œ, Oracleì˜ openJDK í•œì •ìœ¼ë¡œ í´ë˜ìŠ¤ ì•ˆì— ìˆëŠ” ìˆ«ìí˜• ë¦¬í„°ëŸ´ ë°ì´í„°ëŠ” ì–´ë””ì—ì„œ ì–´ë–»ê²Œ ì„ ì–¸ë˜ì—ˆëŠëƒì— ë”°ë¼ ì €ì¥ë˜ëŠ” ìœ„ì¹˜ê°€ ë‹¤ë¥´ë‹¤.
> ë˜í•œ, ë§´ë²„ ë³€ìˆ˜, ë¡œì»¬ ë³€ìˆ˜ì— í• ë‹¹ëœ ìˆ«ìí˜• ë¦¬í„°ëŸ´ ë°ì´í„°ëŠ” Constant Poolì— ì €ì¥ë˜ì–´ ë³€ìˆ˜ê°€ ì°¸ì¡°í•˜ëŠ” ê²ƒì´ ì•„ë‹ˆë¼ ì§ì ‘ ë³€ìˆ˜ì— ê°’ì´ í• ë‹¹ëœë‹¤.

---

#### ğŸ§‘ğŸ»â€ğŸ’» ëŠë‚€ì 
javapë¼ëŠ” ë””ì–´ìƒ˜ë¸”ë§ì„ í†µí•´ "ë‚´ê°€ ì‚¬ìš©í•˜ê³  ìˆëŠ” JavaëŠ” ì–´ë–¤ íŠ¹ì§•ì„ ê°€ì§€ê³  ìˆëŠ”ì§€", "ì‰½ê²Œ ì ‘ê·¼í•  ìˆ˜ ìˆëŠ” ì •ë³´ë¥¼ í•œë²ˆì¯¤ ì˜³ì€ ì •ë³´ì¸ì§€ì— ëŒ€í•œ ë¶„ì„ëŠ¥ë ¥"ì„ ê¸°ë¥´ê¸° ìœ„í•œ ê³¼ì •ì´ì—ˆìŠµë‹ˆë‹¤. 
ë„ë¸ŒëŸ¬ì ¸ìˆëŠ” ê¸°ìˆ ì„ ê°–ë‹¤ì“°ëŠ” ê²ƒì€ ì´ˆì§œ, ì½”ë”ì—¬ë„ í•  ìˆ˜ ìˆëŠ” ì¼ì´ì§€ë§Œ, ê·¸ê²ƒì„ ë¶„ì„í•˜ê³  íŒë‹¨í•´ì„œ ìœ ìš©í•œ ê²ƒì¸ì§€ë¥¼ ë¶„ë³„í•´ë‚´ëŠ” ê²ƒì´ ê°œë°œìë¼ê³  ìƒê°í•©ë‹ˆë‹¤. ê¸°ìˆ ì„ ì‚¬ìš©í•˜ëŠ”ë° ìˆì–´ì„œ ë‚˜ë¦„ì˜ ì´ìœ ì™€ ê·¸ ì´ìœ ë¥¼ ë’·ë°›ì¹¨í•´ì¤„ ìˆ˜ ìˆëŠ” 
ê·¼ê±°ë¥¼ ì œì‹œí•  ìˆ˜ ìˆëŠ” ê°œë°œìê°€ ë˜ê³  ì‹¶ìŠµë‹ˆë‹¤. (ë¬¼ë¡  ë¹ ë¥´ê²Œ êµ¬í˜„í•˜ëŠ” ëŠ¥ë ¥ë„ í‚¤ìš°ê³  ì‹¶ìŠµë‹ˆë‹¤ ğŸ˜)
